gsheet_transformer/__init__.py
tests/__init__.py
tests/conftest.py
gsheet_transformer-0.0.2.dist-info/LICENSE
gsheet_transformer-0.0.2.dist-info/METADATA
gsheet_transformer-0.0.2.dist-info/WHEEL
gsheet_transformer-0.0.2.dist-info/top_level.txt
gsheet_transformer-0.0.2.dist-info/RECORD
