Metadata-Version: 2.1
Name: gsheet-transformer
Version: 0.0.2
Summary: gsheet_transformer created by Koinworks Data Team
Home-page: https://gitlab-engineering.koinworks.com/data-team/gsheet-transformer
Author: Koinworks Data Team
License-File: LICENSE
Requires-Dist: pandas
Requires-Dist: gspread
Provides-Extra: test
Requires-Dist: pytest ; extra == 'test'
Requires-Dist: coverage ; extra == 'test'
Requires-Dist: flake8 ; extra == 'test'
Requires-Dist: black ; extra == 'test'
Requires-Dist: isort ; extra == 'test'
Requires-Dist: pytest-cov ; extra == 'test'
Requires-Dist: codecov ; extra == 'test'
Requires-Dist: mypy ; extra == 'test'
Requires-Dist: gitchangelog ; extra == 'test'
Requires-Dist: mkdocs ; extra == 'test'
Requires-Dist: twine ; extra == 'test'
